LICENSE
README.md
setup.cfg
setup.py
comment_header_creator/__init__.py
comment_header_creator.egg-info/PKG-INFO
comment_header_creator.egg-info/SOURCES.txt
comment_header_creator.egg-info/dependency_links.txt
comment_header_creator.egg-info/top_level.txt