Metadata-Version: 2.1
Name: comment-header-creator
Version: 20210909.0
Summary: Create nicely formatted comment strings to be used as headers/seperators in your code.
Home-page: https://github.com/daxm/python_comment_header_creator
Author: Dax Mickelson
Author-email: dmickels@cisco.com
License: UNKNOWN
Platform: UNKNOWN
Classifier: Programming Language :: Python :: 3
Classifier: License :: OSI Approved :: MIT License
Classifier: Operating System :: OS Independent
Requires-Python: >=3.6
